lambda_trading/__init__.py
lambda_trading/_base_client.py
lambda_trading/_client.py
lambda_trading/_compat.py
lambda_trading/_constants.py
lambda_trading/_exceptions.py
lambda_trading/_files.py
lambda_trading/_models.py
lambda_trading/_qs.py
lambda_trading/_resource.py
lambda_trading/_response.py
lambda_trading/_streaming.py
lambda_trading/_types.py
lambda_trading/_version.py
lambda_trading/py.typed
lambda_trading/_utils/__init__.py
lambda_trading/_utils/_logs.py
lambda_trading/_utils/_proxy.py
lambda_trading/_utils/_reflection.py
lambda_trading/_utils/_streams.py
lambda_trading/_utils/_sync.py
lambda_trading/_utils/_transform.py
lambda_trading/_utils/_typing.py
lambda_trading/_utils/_utils.py
lambda_trading/lib/.keep
lambda_trading/resources/__init__.py
lambda_trading/resources/orders.py
lambda_trading/resources/prices.py
lambda_trading/types/__init__.py
lambda_trading/types/order_buy_params.py
lambda_trading/types/order_buy_response.py
lambda_trading/types/order_open_params.py
lambda_trading/types/order_open_response.py
lambda_trading/types/order_sell_params.py
lambda_trading/types/order_sell_response.py
lambda_trading/types/price_retrieve_params.py
lambda_trading/types/price_retrieve_response.py
lambda_trading-0.1.0a1.dist-info/METADATA
lambda_trading-0.1.0a1.dist-info/WHEEL
lambda_trading-0.1.0a1.dist-info/licenses/LICENSE
lambda_trading-0.1.0a1.dist-info/RECORD
